ament_index_cpp/_dummy.cpython-310-x86_64-linux-gnu.so
ros_ament_index_cpp-1.11.0.data/data/include/ament_index_cpp/ament_index_cpp/get_package_prefix.hpp
ros_ament_index_cpp-1.11.0.data/data/include/ament_index_cpp/ament_index_cpp/get_package_share_directory.hpp
ros_ament_index_cpp-1.11.0.data/data/include/ament_index_cpp/ament_index_cpp/get_packages_with_prefixes.hpp
ros_ament_index_cpp-1.11.0.data/data/include/ament_index_cpp/ament_index_cpp/get_resource.hpp
ros_ament_index_cpp-1.11.0.data/data/include/ament_index_cpp/ament_index_cpp/get_resources.hpp
ros_ament_index_cpp-1.11.0.data/data/include/ament_index_cpp/ament_index_cpp/get_search_paths.hpp
ros_ament_index_cpp-1.11.0.data/data/include/ament_index_cpp/ament_index_cpp/has_resource.hpp
ros_ament_index_cpp-1.11.0.data/data/include/ament_index_cpp/ament_index_cpp/visibility_control.h
ros_ament_index_cpp-1.11.0.data/data/lib/libament_index_cpp.so
ros_ament_index_cpp-1.11.0.data/data/share/ament_index/resource_index/package_run_dependencies/ament_index_cpp
ros_ament_index_cpp-1.11.0.data/data/share/ament_index/resource_index/packages/ament_index_cpp
ros_ament_index_cpp-1.11.0.data/data/share/ament_index/resource_index/parent_prefix_path/ament_index_cpp
ros_ament_index_cpp-1.11.0.data/data/share/ament_index_cpp/local_setup.bash
ros_ament_index_cpp-1.11.0.data/data/share/ament_index_cpp/local_setup.dsv
ros_ament_index_cpp-1.11.0.data/data/share/ament_index_cpp/local_setup.sh
ros_ament_index_cpp-1.11.0.data/data/share/ament_index_cpp/local_setup.zsh
ros_ament_index_cpp-1.11.0.data/data/share/ament_index_cpp/package.dsv
ros_ament_index_cpp-1.11.0.data/data/share/ament_index_cpp/package.xml
ros_ament_index_cpp-1.11.0.data/data/share/ament_index_cpp/cmake/ament_cmake_export_targets-extras.cmake
ros_ament_index_cpp-1.11.0.data/data/share/ament_index_cpp/cmake/ament_index_cppConfig-version.cmake
ros_ament_index_cpp-1.11.0.data/data/share/ament_index_cpp/cmake/ament_index_cppConfig.cmake
ros_ament_index_cpp-1.11.0.dist-info/METADATA
ros_ament_index_cpp-1.11.0.dist-info/WHEEL
ros_ament_index_cpp-1.11.0.dist-info/top_level.txt
ros_ament_index_cpp-1.11.0.dist-info/RECORD
