Metadata-Version: 2.4
Name: ros-ament-index-cpp
Version: 1.11.0
Summary: A ROS package providing a C++ API for programmatic access to the ament resource index.
Dynamic: description
Dynamic: description-content-type
Dynamic: summary
